ayolo/__init__.py
ayolo/__main__.py
ayolo/background.py
ayolo/bugfixes.py
ayolo/commands.py
ayolo/constants.py
ayolo/utilities.py
ayolo/window.py
ayolo-0.2.1.dist-info/LICENSE
ayolo-0.2.1.dist-info/METADATA
ayolo-0.2.1.dist-info/WHEEL
ayolo-0.2.1.dist-info/entry_points.txt
ayolo-0.2.1.dist-info/top_level.txt
ayolo-0.2.1.dist-info/zip-safe
ayolo-0.2.1.dist-info/RECORD
