Metadata-Version: 2.1
Name: ayolo
Version: 0.2.1
Summary: PyQt5 based annotation tool for yolov4 datasets, providing fast and easy ways of annotating.
Home-page: https://github.com/paaksing/ayolo
Author: Paaksing
Author-email: paaksingtech@gmail.com
License: MIT
Keywords: yolov4,annotating,annotations,DNN,deep learning
Platform: UNKNOWN
Classifier: Development Status :: 5 - Production/Stable
Classifier: Programming Language :: Python :: 3.7
Classifier: Environment :: X11 Applications :: Qt
Classifier: Operating System :: OS Independent
Classifier: Intended Audience :: Developers
Classifier: License :: OSI Approved :: MIT License
Classifier: Topic :: Multimedia :: Graphics :: Editors
Classifier: Topic :: Scientific/Engineering :: Artificial Intelligence
Classifier: Topic :: Scientific/Engineering :: Image Recognition
Classifier: Topic :: Scientific/Engineering :: Image Processing
Classifier: Topic :: Utilities
Classifier: Natural Language :: English
Requires-Dist: wheel
Requires-Dist: PyQt5 (==5.15.4)
Requires-Dist: pyqt-darktheme (==1.2.3)
